Metadata-Version: 2.1
Name: wagtail-videos
Version: 2.1.0
Summary: A wagtail module for uploading and displaying videos in various codecs.
Home-page: https://github.com/flytrap/wagtailvideos
Author: Takeflight
Author-email: developers@takeflight.com.au
License: BSD License
Platform: UNKNOWN
Classifier: Environment :: Web Environment
Classifier: Intended Audience :: Developers
Classifier: Operating System :: OS Independent
Classifier: Programming Language :: Python
Classifier: Programming Language :: Python :: 3
Classifier: Programming Language :: Python :: 3.4
Classifier: Programming Language :: Python :: 3.5
Classifier: Programming Language :: Python :: 3.6
Classifier: Framework :: Django
Classifier: License :: OSI Approved :: BSD License
Provides-Extra: testing
